Workbook

Sheet Recolha
B2: Auditoria de Recolha e Integridade dos Dados
B3: Distribuição: Amostra distribuída entre os autores reais.
B5: ID do Post | C5: Jogo | D5: Link do Post | E5: Autor Responsável | F5: Acesso ao Link (OK/Erro) | G5: Correspondência (Sim/Não) | H5: Notas
B6: 3000013_19862910 | C6: World of Warcraft | D6: https://us.forums.blizzard.com/en/wow/t/the-amount-of-botting-in-unacceptable/1525402 | E6: JPaulo | F6: Ok | G6: Sim
B7: 509843_2862478 | C7: EVE Online | D7: https://forums.eveonline.com/t/introducing-exordium/509843/1181 | E7: Roger
B8: 3000009_28801877 | C8: World of Warcraft | D8: https://us.forums.blizzard.com/en/wow/t/does-microsoft-use-any-of-its-ai-technology-for-anything-related-to-world-of-warcraft/2248219 | E8: Emmanoel
B9: 511899_2878208 | C9: EVE Online | D9: https://forums.eveonline.com/t/lol-safezones/511899/196 | E9: Gomide
B10: 509843_2862470 | C10: EVE Online | D10: https://forums.eveonline.com/t/introducing-exordium/509843/1181 | E10: JPaulo | F10: Ok | G10: Sim
B11: 3000012_25620015 | C11: World of Warcraft | D11: https://us.forums.blizzard.com/en/wow/t/will-history-repeat-itself-with-the-bot-crisis-when-the-servers-launch/2012234 | E11: Roger
B12: 3000005_25902774 | C12: World of Warcraft | D12: https://us.forums.blizzard.com/en/wow/t/video-evidence-of-bot/2032803 | E12: Emmanoel
B13: 507777_2846554 | C13: EVE Online | D13: https://forums.eveonline.com/t/separate-space-for-newbies/507777/478 | E13: Gomide
B14: 510142_2865148 | C14: EVE Online | D14: https://forums.eveonline.com/t/nerf-afk-moon-mining/510142/115 | E14: JPaulo | F14: Ok | G14: Sim
B15: 511200_2872613 | C15: EVE Online | D15: https://forums.eveonline.com/t/why-is-ccp-punishing-real-players-while-looking-the-other-way-on-botting/511200/99 | E15: Roger
B16: 511004_2871874 | C16: EVE Online | D16: https://forums.eveonline.com/t/limitation-of-alpha-accounts-to-veterans-omega-account-holders/511004/7 | E16: Emmanoel
B17: 509972_2863229 | C17: EVE Online | D17: https://forums.eveonline.com/t/wondering-how-many-mega-multis-will-be-heading-to-exordium-to-avoid-ganks/509972/582 | E17: Gomide
B18: 3000006_27235331 | C18: World of Warcraft | D18: https://us.forums.blizzard.com/en/wow/t/bots-on-nightslayer/2129768 | E18: JPaulo | F18: Ok | G18: Sim
B19: 3000004_29507115 | C19: World of Warcraft | D19: https://us.forums.blizzard.com/en/wow/t/i-bet-blizzard-could-get-rid-of-99-of-botters-and-scammers-by-just/2307348 | E19: Roger
B20: 511004_2872749 | C20: EVE Online | D20: https://forums.eveonline.com/t/limitation-of-alpha-accounts-to-veterans-omega-account-holders/511004/7 | E20: Emmanoel
B21: 510142_2865138 | C21: EVE Online | D21: https://forums.eveonline.com/t/nerf-afk-moon-mining/510142/115 | E21: Gomide
B22: 509972_2863226 | C22: EVE Online | D22: https://forums.eveonline.com/t/wondering-how-many-mega-multis-will-be-heading-to-exordium-to-avoid-ganks/509972/582 | E22: JPaulo | F22: Ok | G22: Sim
B23: 509129_2863227 | C23: EVE Online | D23: https://forums.eveonline.com/t/team-security-2026-bans/509129/124 | E23: Roger
B24: 1qkbren_5 | C24: EVE Online | D24: http://reddit.com/r/Eve/comments/1qkbren/are_gms_just_happy_with_pochven_botting/ | E24: Emmanoel
B25: 3000006_27253889 | C25: World of Warcraft | D25: https://us.forums.blizzard.com/en/wow/t/bots-on-nightslayer/2129768 | E25: Gomide
B26: 1beecfw_1 | C26: World of Warcraft | D26: https://www.reddit.com/r/woweconomy/comments/1beecfw/bots_are_going_to_get_a_lot_worse_and_completely_ruin_the_economy/ | E26: JPaulo | F26: Ok | G26: Sim
B27: 514029_2896571 | C27: EVE Online | D27: https://forums.eveonline.com/t/game-breaking-lack-of-enforcement-against-input-broadcasting-multi-input-automation/514029/34 | E27: Roger
B28: 511200_2873852 | C28: EVE Online | D28: https://forums.eveonline.com/t/why-is-ccp-punishing-real-players-while-looking-the-other-way-on-botting/511200/99 | E28: Emmanoel
B29: 18m0xzk_4 | C29: EVE Online | D29: https://www.reddit.com/r/Eve/comments/18m0xzk/first_time_ive_noticed_market_manipulation_in_the/ | E29: Gomide
B30: 3000013_19863281 | C30: World of Warcraft | D30: https://us.forums.blizzard.com/en/wow/t/the-amount-of-botting-in-unacceptable/1525402 | E30: JPaulo | F30: Ok | G30: Sim
B31: 1s424mo_1 | C31: World of Warcraft | D31: https://www.reddit.com/r/classicwow/comments/1s424mo/botting_actually_helps_the_economy/ | E31: Roger
B32: 487448_2723767 | C32: EVE Online | D32: https://forums.eveonline.com/t/economy-thread/487448/22 | E32: Emmanoel
B33: 1675072_21541815 | C33: World of Warcraft | D33: https://us.forums.blizzard.com/en/wow/t/change-to-reporting-system-is-helping-bots-massively/1675072 | E33: Gomide
B34: 514029_2896860 | C34: EVE Online | D34: https://forums.eveonline.com/t/game-breaking-lack-of-enforcement-against-input-broadcasting-multi-input-automation/514029/34 | E34: JPaulo | F34: Ok | G34: Sim
B35: 3000008_25929662 | C35: World of Warcraft | D35: https://us.forums.blizzard.com/en/wow/t/all-of-the-bad-none-of-the-good/2034435 | E35: Roger

Sheet Filtragem
B2: Auditoria de Filtragem Semântica (Falsos Negativos)
B3: Distribuição: Avaliação de posts para caça a gírias/sarcasmos não reconhecidos.
C5: Linl | D5: Jogo | E5: Autor Responsável | F5: Contém Gíria/Sarcasmo? | G5: Falso Negativo? (Sim/Não) | H5: Justificação
B6: 3000013_19862910 | C6: {=XLOOKUP(B6, Recolha!B6:B36, Recolha!D6:D36, "Não encontrado")} -> https://us.forums.blizzard.com/en/wow/t/the-amount-of-botting-in-unacceptable/1525402 | D6: World of Warcraft | E6: Roger
B7: 509843_2862478 | C7: {=XLOOKUP(B7, Recolha!B7:B37, Recolha!D7:D37, "Não encontrado")} -> https://forums.eveonline.com/t/introducing-exordium/509843/1181 | D7: EVE Online | E7: Emmanoel
B8: 3000009_28801877 | C8: {=XLOOKUP(B8, Recolha!B8:B38, Recolha!D8:D38, "Não encontrado")} -> https://us.forums.blizzard.com/en/wow/t/does-microsoft-use-any-of-its-ai-technology-for-anything-related-to-world-of-warcraft/2248219 | D8: World of Warcraft | E8: Gomide
B9: 511899_2878208 | C9: {=XLOOKUP(B9, Recolha!B9:B39, Recolha!D9:D39, "Não encontrado")} -> https://forums.eveonline.com/t/lol-safezones/511899/196 | D9: EVE Online | E9: JPaulo
B10: 509843_2862470 | C10: {=XLOOKUP(B10, Recolha!B10:B40, Recolha!D10:D40, "Não encontrado")} -> https://forums.eveonline.com/t/introducing-exordium/509843/1181 | D10: EVE Online | E10: Roger
B11: 3000012_25620015 | C11: {=XLOOKUP(B11, Recolha!B11:B41, Recolha!D11:D41, "Não encontrado")} -> https://us.forums.blizzard.com/en/wow/t/will-history-repeat-itself-with-the-bot-crisis-when-the-servers-launch/2012234 | D11: World of Warcraft | E11: Emmanoel
B12: 3000005_25902774 | C12: {=XLOOKUP(B12, Recolha!B12:B42, Recolha!D12:D42, "Não encontrado")} -> https://us.forums.blizzard.com/en/wow/t/video-evidence-of-bot/2032803 | D12: World of Warcraft | E12: Gomide
B13: 507777_2846554 | C13: {=XLOOKUP(B13, Recolha!B13:B43, Recolha!D13:D43, "Não encontrado")} -> https://forums.eveonline.com/t/separate-space-for-newbies/507777/478 | D13: EVE Online | E13: JPaulo
B14: 510142_2865148 | C14: {=XLOOKUP(B14, Recolha!B14:B44, Recolha!D14:D44, "Não encontrado")} -> https://forums.eveonline.com/t/nerf-afk-moon-mining/510142/115 | D14: EVE Online | E14: Roger
B15: 511200_2872613 | C15: {=XLOOKUP(B15, Recolha!B15:B45, Recolha!D15:D45, "Não encontrado")} -> https://forums.eveonline.com/t/why-is-ccp-punishing-real-players-while-looking-the-other-way-on-botting/511200/99 | D15: EVE Online | E15: Emmanoel
B16: 511004_2871874 | C16: {=XLOOKUP(B16, Recolha!B16:B46, Recolha!D16:D46, "Não encontrado")} -> https://forums.eveonline.com/t/limitation-of-alpha-accounts-to-veterans-omega-account-holders/511004/7 | D16: EVE Online | E16: Gomide
B17: 509972_2863229 | C17: {=XLOOKUP(B17, Recolha!B17:B47, Recolha!D17:D47, "Não encontrado")} -> https://forums.eveonline.com/t/wondering-how-many-mega-multis-will-be-heading-to-exordium-to-avoid-ganks/509972/582 | D17: EVE Online | E17: JPaulo
... B25: 3000006_27253889 | C25: {=XLOOKUP(B25, Recolha!B25:B55, Recolha!D25:D55, "Não encontrado")} -> https://us.forums.blizzard.com/en/wow/t/bots-on-nightslayer/2129768 | D25: World of Warcraft | E25: JPaulo

Sheet Codificação A3
B2: Grelha de Codificação Independente — Repositório 3
B3: Instruções: Insira a sua classificação sem ver as respostas dos colegas ou da IA.
B5: ID do Post | C5: Jogo | D5: Texto do Post | E5: Codificador Humano | F5: Dimensão DART | G5: Cocriação | H5: Notas
B6: 3000013_19862910 | C6: World of Warcraft | D6: I don’t think at any point in Classic (maybe in the history of WoW) has botting been as much of an issue as it is currently. It’s actually at the point where its effecting gameplay on a regular basis, especially in bgs, even at 80. This is unacceptable. | E6: JPaulo
B7: 509843_2862478 | C7: EVE Online | D7: If they limit the ship types which can use the Shipcasters then this would prevent Rookieville being used as a hauling shortcut. | E7: Roger
B8: 3000009_28801877 | C8: World of Warcraft | D8: Very different definition of “AI”. Part of the problem in these discussions, the LLM-bros took the term “AI” both for the marketing hype and fluffery, and to confuse people. On the stuff the LLM-bros are pushing… [URL_ANONYMIZED] – the cost of AI, and who is really pushing it [URL_ANONYMIZED] – B... | E8: Emmanoel
B9: 511899_2878208 | C9: EVE Online | D9: I got can baited and destroyed about 10 minutes into making my account. I’m sad new players will no longer experience that. | E9: Gomide
B10: 509843_2862470 | C10: EVE Online | D10: I guess the high special taxes in there will make it unlucrative to build anything for sale. Funnily, this will also sour the interest of newbies into those activities. Which might be part of the plan as CCP desperately wants to sell ships for cash, not for time mined. | E10: JPaulo
B11: 3000012_25620015 | C11: World of Warcraft | D11: I remember way back when classic launched the level of bots were insane. Whole armies of them running into stockades etc? It’s great to see all the QoL changes coming, but will the elephant in the room actually be addressed? Or will the economy be trashed, again? | E11: Roger
B12: 3000005_25902774 | C12: World of Warcraft | D12: Alsharptusk: Raising bot awareness is helpful even if Blizzard never see this. people are well aware of bots in the game. pretty much anygame where profit can be made in fact. | E12: Emmanoel
B13: 507777_2846554 | C13: EVE Online | D13: Who knows if this update really helps new players but one thing is certain and that it how this space can be abused by old players. | E13: Gomide
B14: 510142_2865148 | C14: EVE Online | D14: Eaglefeather: Drones are no different than hull mounted guns Sure they are. They are separate objects, targetable, destroyable, can remain on grid if the ship warps away. Destroying them doesn’t endanger the capsuleer. Process of deploying them to space is even the same as with all othe deploy... | E14: JPaulo
B15: 511200_2872613 | C15: EVE Online | D15: Exactly, CCP prefers short-term PLEX profit over the long-term health of the player base | E15: Roger
B16: 511004_2871874 | C16: EVE Online | D16: I don’t think you understand that ALL cases of “BOTTING” (which is how ccp classifies all these) are already reviewed by staff? | E16: Emmanoel
B17: 509972_2863229 | C17: EVE Online | D17: Already devaluing something new before it’s even live? Because it ‘changes something’? So typical and so static… | E17: Gomide
... B55: 513682_2893002 | C55: EVE Online | D55: Lokar Griman: The problem is that when players repeatedly report the same behaviour from same group and see no visible improvement, they simply stop participating. If Fenris takes no action (bear in mind that it can take them months to do it!), then it probably wasn’t input broadcasting, or it... | E55: Roger

Sheet Codificação A4
B2: Grelha de Codificação Independente — Repositório 4
B3: Instruções: Insira a sua classificação sem ver as respostas dos colegas ou da IA.
B5: ID do Post | C5: Jogo | D5: Texto do Post | E5: Codificador Humano | F5: Dimensão DART | G5: Cocriação | H5: Notas
B6: 3000013_19862910 | C6: World of Warcraft | D6: I don’t think at any point in Classic (maybe in the history of WoW) has botting been as much of an issue as it is currently. It’s actually at the point where its effecting gameplay on a regular basis, especially in bgs, even at 80. This is unacceptable. | E6: Roger
B7: 509843_2862478 | C7: EVE Online | D7: If they limit the ship types which can use the Shipcasters then this would prevent Rookieville being used as a hauling shortcut. | E7: Emmanoel
B8: 3000009_28801877 | C8: World of Warcraft | D8: Very different definition of “AI”. Part of the problem in these discussions, the LLM-bros took the term “AI” both for the marketing hype and fluffery, and to confuse people. On the stuff the LLM-bros are pushing… [URL_ANONYMIZED] – the cost of AI, and who is really pushing it [URL_ANONYMIZED] – B... | E8: Gomide
B9: 511899_2878208 | C9: EVE Online | D9: I got can baited and destroyed about 10 minutes into making my account. I’m sad new players will no longer experience that. | E9: JPaulo
B10: 509843_2862470 | C10: EVE Online | D10: I guess the high special taxes in there will make it unlucrative to build anything for sale. Funnily, this will also sour the interest of newbies into those activities. Which might be part of the plan as CCP desperately wants to sell ships for cash, not for time mined. | E10: Roger
B11: 3000012_25620015 | C11: World of Warcraft | D11: I remember way back when classic launched the level of bots were insane. Whole armies of them running into stockades etc? It’s great to see all the QoL changes coming, but will the elephant in the room actually be addressed? Or will the economy be trashed, again? | E11: Emmanoel
B12: 3000005_25902774 | C12: World of Warcraft | D12: Alsharptusk: Raising bot awareness is helpful even if Blizzard never see this. people are well aware of bots in the game. pretty much anygame where profit can be made in fact. | E12: Gomide
B13: 507777_2846554 | C13: EVE Online | D13: Who knows if this update really helps new players but one thing is certain and that it how this space can be abused by old players. | E13: JPaulo
B14: 510142_2865148 | C14: EVE Online | D14: Eaglefeather: Drones are no different than hull mounted guns Sure they are. They are separate objects, targetable, destroyable, can remain on grid if the ship warps away. Destroying them doesn’t endanger the capsuleer. Process of deploying them to space is even the same as with all othe deploy... | E14: Roger
B15: 511200_2872613 | C15: EVE Online | D15: Exactly, CCP prefers short-term PLEX profit over the long-term health of the player base | E15: Emmanoel
B16: 511004_2871874 | C16: EVE Online | D16: I don’t think you understand that ALL cases of “BOTTING” (which is how ccp classifies all these) are already reviewed by staff? | E16: Gomide
B17: 509972_2863229 | C17: EVE Online | D17: Already devaluing something new before it’s even live? Because it ‘changes something’? So typical and so static… | E17: JPaulo
... B55: 513682_2893002 | C55: EVE Online | D55: Lokar Griman: The problem is that when players repeatedly report the same behaviour from same group and see no visible improvement, they simply stop participating. If Fenris takes no action (bear in mind that it can take them months to do it!), then it probably wasn’t input broadcasting, or it... | E55: Emmanoel

Sheet Comparação e Kappa
B2: Módulo Estatístico de Concordância e Extração de Dados
B5: Resultados Estimados do Índice Kappa de Cohen
B6: Dimensão Metodológica | C6: Concordância Observada (Po) | D6: Concordância Aleatória (Pe) | E6: Cohen's Kappa (κ) | F6: Interpretação
B7: Dimensão DART | F7: =IF(E7>0.8, "Quase Perfeita", IF(E7>0.6, "Substancial", IF(E7>0.4, "Moderada", "Fraca"))) -> Fraca
B8: Tipologia de Interação (Cocriação) | F8: =IF(E8>0.8, "Quase Perfeita", IF(E8>0.6, "Substancial", IF(E8>0.4, "Moderada", "Fraca"))) -> Fraca
B11: Mesa de Consenso Humano-vs-IA (Alvo de Extração para o Script de IA)
B12: Mapeamento exato do seu CSV. O script deve ler as colunas B até I a partir da linha 14.
B14: ID do Post | C14: Jogo | D14: Link do Post | E14: Texto do Post | F14: DART_IA | G14: Cocriacao_IA | H14: DART_Humano | I14: Cocriacao_Humano | J14: DART Coincide? (Fórmula) | K14: Cocriação Coincide? (Fórmula)
B15: 3000013_19862910 | C15: World of Warcraft | D15: https://us.forums.blizzard.com/en/wow/t/the-amount-of-botting-in-unacceptable/1525402 | E15: I don’t think at any point in Classic (maybe in the history of WoW) has botting been as much of an issue as it is currently. It’s actually at the point where its effecting gameplay on a regular basis, especially in bgs, even at 80. This is unacceptable. | F15: risco | G15: parasitaria | J15: =IF(H15="", "", IF(F15=H15, 1, 0)) | K15: =IF(I15="", "", IF(G15=I15, 1, 0))
B16: 509843_2862478 | C16: EVE Online | D16: https://forums.eveonline.com/t/introducing-exordium/509843/1181 | E16: If they limit the ship types which can use the Shipcasters then this would prevent Rookieville being used as a hauling shortcut. | F16: dialogo | G16: simetrica | J16: =IF(H16="", "", IF(F16=H16, 1, 0)) | K16: =IF(I16="", "", IF(G16=I16, 1, 0))
B17: 3000009_28801877 | C17: World of Warcraft | D17: https://us.forums.blizzard.com/en/wow/t/does-microsoft-use-any-of-its-ai-technology-for-anything-related-to-world-of-warcraft/2248219 | E17: Very different definition of “AI”. Part of the problem in these discussions, the LLM-bros took the term “AI” both for the marketing hype and fluffery, and to confuse people. On the stuff the LLM-bros are pushing… [URL_ANONYMIZED] – the cost of AI, and who is really pushing it [URL_ANONYMIZED] – B... | F17: dialogo | G17: assimetrica | J17: =IF(H17="", "", IF(F17=H17, 1, 0)) | K17: =IF(I17="", "", IF(G17=I17, 1, 0))
B18: 511899_2878208 | C18: EVE Online | D18: https://forums.eveonline.com/t/lol-safezones/511899/196 | E18: I got can baited and destroyed about 10 minutes into making my account. I’m sad new players will no longer experience that. | F18: risco | G18: assimetrica | J18: =IF(H18="", "", IF(F18=H18, 1, 0)) | K18: =IF(I18="", "", IF(G18=I18, 1, 0))
B19: 509843_2862470 | C19: EVE Online | D19: https://forums.eveonline.com/t/introducing-exordium/509843/1181 | E19: I guess the high special taxes in there will make it unlucrative to build anything for sale. Funnily, this will also sour the interest of newbies into those activities. Which might be part of the plan as CCP desperately wants to sell ships for cash, not for time mined. | F19: acesso | G19: parasitaria | J19: =IF(H19="", "", IF(F19=H19, 1, 0)) | K19: =IF(I19="", "", IF(G19=I19, 1, 0))
B20: 3000012_25620015 | C20: World of Warcraft | D20: https://us.forums.blizzard.com/en/wow/t/will-history-repeat-itself-with-the-bot-crisis-when-the-servers-launch/2012234 | E20: I remember way back when classic launched the level of bots were insane. Whole armies of them running into stockades etc? It’s great to see all the QoL changes coming, but will the elephant in the room actually be addressed? Or will the economy be trashed, again? | F20: dialogo | G20: parasitaria | J20: =IF(H20="", "", IF(F20=H20, 1, 0)) | K20: =IF(I20="", "", IF(G20=I20, 1, 0))
B21: 3000005_25902774 | C21: World of Warcraft | D21: https://us.forums.blizzard.com/en/wow/t/video-evidence-of-bot/2032803 | E21: Alsharptusk: Raising bot awareness is helpful even if Blizzard never see this. people are well aware of bots in the game. pretty much anygame where profit can be made in fact. | F21: risco | G21: parasitaria | J21: =IF(H21="", "", IF(F21=H21, 1, 0)) | K21: =IF(I21="", "", IF(G21=I21, 1, 0))
B22: 507777_2846554 | C22: EVE Online | D22: https://forums.eveonline.com/t/separate-space-for-newbies/507777/478 | E22: Who knows if this update really helps new players but one thing is certain and that it how this space can be abused by old players. | F22: acesso | G22: parasitaria | J22: =IF(H22="", "", IF(F22=H22, 1, 0)) | K22: =IF(I22="", "", IF(G22=I22, 1, 0))
B23: 510142_2865148 | C23: EVE Online | D23: https://forums.eveonline.com/t/nerf-afk-moon-mining/510142/115 | E23: Eaglefeather: Drones are no different than hull mounted guns Sure they are. They are separate objects, targetable, destroyable, can remain on grid if the ship warps away. Destroying them doesn’t endanger the capsuleer. Process of deploying them to space is even the same as with all othe deploy... | F23: dialogo | G23: simetrica | J23: =IF(H23="", "", IF(F23=H23, 1, 0)) | K23: =IF(I23="", "", IF(G23=I23, 1, 0))
B24: 511200_2872613 | C24: EVE Online | D24: https://forums.eveonline.com/t/why-is-ccp-punishing-real-players-while-looking-the-other-way-on-botting/511200/99 | E24: Exactly, CCP prefers short-term PLEX profit over the long-term health of the player base | F24: risco | G24: parasitaria | J24: =IF(H24="", "", IF(F24=H24, 1, 0)) | K24: =IF(I24="", "", IF(G24=I24, 1, 0))
B25: 511004_2871874 | C25: EVE Online | D25: https://forums.eveonline.com/t/limitation-of-alpha-accounts-to-veterans-omega-account-holders/511004/7 | E25: I don’t think you understand that ALL cases of “BOTTING” (which is how ccp classifies all these) are already reviewed by staff? | F25: risco | G25: assimetrica | J25: =IF(H25="", "", IF(F25=H25, 1, 0)) | K25: =IF(I25="", "", IF(G25=I25, 1, 0))
B26: 509972_2863229 | C26: EVE Online | D26: https://forums.eveonline.com/t/wondering-how-many-mega-multis-will-be-heading-to-exordium-to-avoid-ganks/509972/582 | E26: Already devaluing something new before it’s even live? Because it ‘changes something’? So typical and so static… | F26: acesso | G26: parasitaria | J26: =IF(H26="", "", IF(F26=H26, 1, 0)) | K26: =IF(I26="", "", IF(G26=I26, 1, 0))
... B64: 513682_2893002 | C64: EVE Online | D64: https://forums.eveonline.com/t/input-broadcasters-or-similar-programs/513682/30 | E64: Lokar Griman: The problem is that when players repeatedly report the same behaviour from same group and see no visible improvement, they simply stop participating. If Fenris takes no action (bear in mind that it can take them months to do it!), then it probably wasn’t input broadcasting, or it... | F64: dialogo | G64: parasitaria | J64: =IF(H64="", "", IF(F64=H64, 1, 0)) | K64: =IF(I64="", "", IF(G64=I64, 1, 0))

Sheet Reconciliação
B2: Resolução Coletiva de Discrepâncias
B5: ID do Post | C5: Variável Em Disputa | D5: Voto Codificador 1 | E5: Voto Codificador 2 | F5: Consenso Final | G5: Regra de Ouro/Teórica Aplicada

Sheet Anonimização
B2: Auditoria Ética e Desinfetização
B5: ID do Post | C5: Autor Revisor | D5: Username Pseudonimizado? | E5: Links de Hacks Removidos? | F5: Status de Conformidade
B6: 3000013_19862910 | C6: JPaulo
B7: 509843_2862478 | C7: Roger
B8: 3000009_28801877 | C8: Emmanoel
B9: 511899_2878208 | C9: Gomide
B10: 509843_2862470 | C10: JPaulo
B11: 3000012_25620015 | C11: Roger
B12: 3000005_25902774 | C12: Emmanoel
B13: 507777_2846554 | C13: Gomide
B14: 510142_2865148 | C14: JPaulo
B15: 511200_2872613 | C15: Roger
B16: 511004_2871874 | C16: Emmanoel
B17: 509972_2863229 | C17: Gomide
... B25: 3000006_27253889 | C25: Gomide

Sheet Síntese Final
B2: Checklist de Coerência e Redação Final
B5: Componente Científica | C5: Critério de Verificação Empírica | D5: Autor Revisor | E5: Estado
B6: Estatísticas Comparativas | C6: As métricas (WoW vs. EVE) no ficheiro .md batem certo com o encadeamento dos dados? | D6: ? | E6: Pendente
B7: Questões de Investigação | C7: As 5 QIs foram respondidas com base nas citações empíricas validadas? | D7: ? | E7: Pendente
B8: Prevenção de Alucinações | C8: Auditoria de 100% das citações diretas integradas contra os textos originais. | D8: ? | E8: Pendente
B9: Limites Metodológicos | C9: A secção de limitações reflete a transição do score interno para o Kappa humano? | D9: ? | E9: Pendente
